jiushu_logger/__init__.py
jiushu_logger/ai_model_log.py
jiushu_logger/helpers.py
jiushu_logger/log.py
jiushu_logger-1.0.6.dist-info/LICENSE
jiushu_logger-1.0.6.dist-info/WHEEL
jiushu_logger-1.0.6.dist-info/METADATA
jiushu_logger-1.0.6.dist-info/RECORD
