Metadata-Version: 2.1
Name: jiushu_logger
Version: 1.0.6
Summary: A logger with standardized format for JF.
Author-email: Ai Tutu <zhixiao.yang0124@gmail.com>
Requires-Python: >=3.7
Classifier: License :: OSI Approved :: The Unlicense (Unlicense)
Classifier: Operating System :: OS Independent
Classifier: Programming Language :: Python :: 3
Classifier: Topic :: System :: Logging
Classifier: Typing :: Typed
Requires-Dist: httpx>=0.23.0
Requires-Dist: orjson>=3.8.0
Project-URL: Bug Tracker, https://github.com/XiaoxiaFamily/jiushu-logger/issues
Project-URL: Homepage, https://github.com/XiaoxiaFamily/jiushu-logger
